LICENSE
py_ocpi/__init__.py
py_ocpi/core/__init__.py
py_ocpi/core/adapter.py
py_ocpi/core/config.py
py_ocpi/core/crud.py
py_ocpi/core/data_types.py
py_ocpi/core/dependencies.py
py_ocpi/core/endpoints.py
py_ocpi/core/enums.py
py_ocpi/core/exceptions.py
py_ocpi/core/push.py
py_ocpi/core/schemas.py
py_ocpi/core/status.py
py_ocpi/core/utils.py
py_ocpi/main.py
py_ocpi/modules/__init__.py
py_ocpi/modules/cdrs/__init__.py
py_ocpi/modules/cdrs/v_2_2_1/api/__init__.py
py_ocpi/modules/cdrs/v_2_2_1/api/cpo.py
py_ocpi/modules/cdrs/v_2_2_1/api/emsp.py
py_ocpi/modules/cdrs/v_2_2_1/enums.py
py_ocpi/modules/cdrs/v_2_2_1/schemas.py
py_ocpi/modules/commands/__init__.py
py_ocpi/modules/commands/v_2_2_1/api/__init__.py
py_ocpi/modules/commands/v_2_2_1/api/cpo.py
py_ocpi/modules/commands/v_2_2_1/api/emsp.py
py_ocpi/modules/commands/v_2_2_1/enums.py
py_ocpi/modules/commands/v_2_2_1/schemas.py
py_ocpi/modules/credentials/__init__.py
py_ocpi/modules/credentials/v_2_2_1/api/__init__.py
py_ocpi/modules/credentials/v_2_2_1/api/cpo.py
py_ocpi/modules/credentials/v_2_2_1/api/emsp.py
py_ocpi/modules/credentials/v_2_2_1/enums.py
py_ocpi/modules/credentials/v_2_2_1/schemas.py
py_ocpi/modules/locations/__init__.py
py_ocpi/modules/locations/v_2_2_1/api/__init__.py
py_ocpi/modules/locations/v_2_2_1/api/cpo.py
py_ocpi/modules/locations/v_2_2_1/api/emsp.py
py_ocpi/modules/locations/v_2_2_1/enums.py
py_ocpi/modules/locations/v_2_2_1/schemas.py
py_ocpi/modules/sessions/__init__.py
py_ocpi/modules/sessions/v_2_2_1/api/__init__.py
py_ocpi/modules/sessions/v_2_2_1/api/cpo.py
py_ocpi/modules/sessions/v_2_2_1/api/emsp.py
py_ocpi/modules/sessions/v_2_2_1/enums.py
py_ocpi/modules/sessions/v_2_2_1/schemas.py
py_ocpi/modules/tariffs/__init__.py
py_ocpi/modules/tariffs/v_2_2_1/api/__init__.py
py_ocpi/modules/tariffs/v_2_2_1/api/cpo.py
py_ocpi/modules/tariffs/v_2_2_1/api/emsp.py
py_ocpi/modules/tariffs/v_2_2_1/enums.py
py_ocpi/modules/tariffs/v_2_2_1/schemas.py
py_ocpi/modules/tokens/__init__.py
py_ocpi-0.3.1.dist-info/LICENSE
py_ocpi-0.3.1.dist-info/METADATA
py_ocpi-0.3.1.dist-info/WHEEL
py_ocpi-0.3.1.dist-info/RECORD
