Metadata-Version: 2.1
Name: py-ocpi
Version: 0.3.1
Summary: Python Implementation of OCPI
Home-page: https://github.com/TECHS-Technological-Solutions/ocpi
License: MIT
Keywords: ocpi
Author: HAkhavan71
Author-email: hakh.27@gmail.com
Requires-Python: >=3.9,<4.0
Classifier: License :: OSI Approved :: MIT License
Classifier: Programming Language :: Python :: 3
Classifier: Programming Language :: Python :: 3.9
Classifier: Programming Language :: Python :: 3.10
Classifier: Programming Language :: Python :: 3.11
Requires-Dist: fastapi (>=0.68.0,<0.69.0)
Requires-Dist: httpx (>=0.23.0,<0.24.0)
